au_iomanager/__init__.py
au_iomanager/base.py
au_iomanager/input.py
au_iomanager/output.py
au_iomanager-0.1.3.dist-info/METADATA
au_iomanager-0.1.3.dist-info/WHEEL
au_iomanager-0.1.3.dist-info/RECORD
