Metadata-Version: 2.3
Name: au_iomanager
Version: 0.1.3
Summary: Librería para gestión de datos y ML pipelines
Author: Faustino Lopez Ramos
Author-email: faustinolopezramos@gmail.com
Requires-Python: >=3.8,<4.0
Classifier: Programming Language :: Python :: 3
Classifier: Programming Language :: Python :: 3.8
Classifier: Programming Language :: Python :: 3.9
Classifier: Programming Language :: Python :: 3.10
Classifier: Programming Language :: Python :: 3.11
Classifier: Programming Language :: Python :: 3.12
Classifier: Programming Language :: Python :: 3.13
Requires-Dist: loguru (>=0.7.0)
Requires-Dist: pandas (>=1.0)
